{
  "scenario_script_path": "src/scripts/hiv/projections_jan2023/impact_analysis_tb_DAH.py",
  "scenario_seed": [
    48040
  ],
  "runs_per_draw": 10,
  "draws": [
    {
      "draw_number": 0,
      "draw_seed": 333313577,
      "parameters": {
        "Tb": {
          "scenario": 0
        }
      }
    },
    {
      "draw_number": 1,
      "draw_seed": 298471967,
      "parameters": {
        "Tb": {
          "scenario": 1,
          "first_line_test": "sputum",
          "second_line_test": "sputum"
        }
      }
    },
    {
      "draw_number": 2,
      "draw_seed": 413107634,
      "parameters": {
        "Tb": {
          "scenario": 2
        }
      }
    },
    {
      "draw_number": 3,
      "draw_seed": 1993620351,
      "parameters": {
        "Tb": {
          "scenario": 3
        }
      }
    },
    {
      "draw_number": 4,
      "draw_seed": 933584936,
      "parameters": {
        "Tb": {
          "scenario": 4
        }
      }
    },
    {
      "draw_number": 5,
      "draw_seed": 495753562,
      "parameters": {
        "Tb": {
          "scenario": 5
        }
      }
    },
    {
      "draw_number": 6,
      "draw_seed": 1027705959,
      "parameters": {
        "Tb": {
          "scenario": 6
        }
      }
    },
    {
      "draw_number": 7,
      "draw_seed": 686504325,
      "parameters": {
        "Tb": {
          "scenario": 0,
          "probability_community_chest_xray": 0.1,
          "scaling_factor_WHO": 1.9
        }
      }
    },
    {
      "draw_number": 8,
      "draw_seed": 447452104,
      "parameters": {
        "Tb": {
          "scenario": 0,
          "probability_community_chest_xray": 0.2,
          "scaling_factor_WHO": 1.9
        }
      }
    },
    {
      "draw_number": 9,
      "draw_seed": 61704391,
      "parameters": {
        "Tb": {
          "scenario": 0,
          "probability_community_chest_xray": 0.3,
          "scaling_factor_WHO": 1.9
        }
      }
    }
  ],
  "commit": "89868468dfe6fddb9f228ee7d7849caec3d29507",
  "github": "https://github.com/UCL/TLOmodel/tree/89868468dfe6fddb9f228ee7d7849caec3d29507"
}